hubblepy/__init__.py
hubblepy/api.py
hubblepy-1.0.0.dist-info/DESCRIPTION.rst
hubblepy-1.0.0.dist-info/METADATA
hubblepy-1.0.0.dist-info/RECORD
hubblepy-1.0.0.dist-info/WHEEL
hubblepy-1.0.0.dist-info/metadata.json
hubblepy-1.0.0.dist-info/top_level.txt
